test_autoz/__init__.py
test_autoz/core.py
test_autoz/log.py
test_autoz/server.py
test_autoz-0.1.1.dist-info/METADATA
test_autoz-0.1.1.dist-info/WHEEL
test_autoz-0.1.1.dist-info/top_level.txt
test_autoz-0.1.1.dist-info/RECORD
